alleycat/reactive/__init__.py
alleycat/reactive/functions.py
alleycat/reactive/object.py
alleycat/reactive/property.py
alleycat/reactive/utils.py
alleycat/reactive/value.py
alleycat/reactive/view.py
alleycat_reactive-0.4.8.dist-info/LICENSE
alleycat_reactive-0.4.8.dist-info/METADATA
alleycat_reactive-0.4.8.dist-info/WHEEL
alleycat_reactive-0.4.8.dist-info/top_level.txt
alleycat_reactive-0.4.8.dist-info/RECORD
