Metadata-Version: 2.1
Name: alleycat-reactive
Version: 0.4.8
Summary: A simple Python library to provide an API to implement the Reactive Object Pattern (ROP).
Home-page: https://github.com/mysticfall/alleycat-reactive
Author: Xavier Cho
Author-email: mysticfallband@gmail.com
License: UNKNOWN
Platform: UNKNOWN
Classifier: Programming Language :: Python :: 3
Classifier: License :: OSI Approved :: MIT License
Classifier: Operating System :: OS Independent
License-File: LICENSE
Requires-Dist: returns (==0.17.0)
Requires-Dist: rx (==3.2.0)
